pytinyexr.cpython-36m-i386-linux-gnu.so
pytinyexr-0.9.1.dist-info/top_level.txt
pytinyexr-0.9.1.dist-info/RECORD
pytinyexr-0.9.1.dist-info/METADATA
pytinyexr-0.9.1.dist-info/WHEEL
