Metadata-Version: 2.1
Name: pytinyexr
Version: 0.9.1
Summary: Python bindings for TinyEXR(OpenEXR loader/saver)
Home-page: https://github.com/syoyo/PyEXR
Author: Syoyo Fujita
Author-email: 
License: UNKNOWN
Project-URL: Issue Tracker, https://github.com/syoyo/PyEXR/issues
Platform: UNKNOWN
Classifier: Development Status :: 5 - Production/Stable
Classifier: Intended Audience :: Developers
Classifier: Intended Audience :: Science/Research
Classifier: Intended Audience :: Manufacturing
Classifier: Topic :: Artistic Software
Classifier: Topic :: Multimedia :: Graphics :: 3D Modeling
Classifier: Topic :: Scientific/Engineering :: Visualization
Classifier: License :: OSI Approved :: MIT License
Classifier: Operating System :: OS Independent
Classifier: Programming Language :: Python :: 3
